
{
  "google_pixel_phones": [
    {
      "model": "Google Pixel 9",
      "original_price": "₹59,550",
      "final_price": "₹55,977",
      "network": "Dual Sim, 3G, 4G, 5G, VoLTE, Vo5G, Wi-Fi, NFC",
      "processor": "Tensor G4, Octa Core, 3.1 GHz Processor",
      "memory": "12 GB RAM, 256 GB inbuilt",
      "battery": "4700 mAh Battery with 27W Fast Charging",
      "display": "6.3 inches, 1080 x 2424 px, 120 Hz Display with Punch Hole",
      "camera": "50 MP + 48 MP Dual Rear & 10.5 MP Front Camera",
      "os": "Android v14",
      "fm_radio": "No FM Radio",
      "spec_score": "87",
      "availability": "Available",
      "store": "amazon"
    },
    {
      "model": "Google Pixel 10 5G",
      "original_price": "₹69,650",
      "final_price": "₹69,650",
      "network": "Dual Sim, 3G, 4G, 5G, VoLTE, Vo5G, Wi-Fi, NFC",
      "processor": "Tensor G5",
      "memory": "12 GB RAM, 256 GB inbuilt",
      "battery": "4970 mAh Battery with 30W Fast Charging",
      "display": "6.3 inches, 1080 x 2424 px, 120 Hz Display with Punch Hole",
      "camera": "48 MP + 13 MP + 10.8 MP Triple Rear & 10.5 MP Front Camera",
      "os": "Android v16",
      "fm_radio": "No FM Radio",
      "spec_score": "79",
      "availability": "Available",
      "store": "amazon"
    },
    {
      "model": "Google Pixel 6 Pro",
      "original_price": "₹29,899",
      "final_price": "₹29,600",
      "network": "Dual Sim, 3G, 4G, 5G, VoLTE, Wi-Fi, NFC",
      "processor": "Tensor, Octa Core, 2.8 GHz Processor",
      "memory": "12 GB RAM, 128 GB inbuilt",
      "battery": "5003 mAh Battery with 30W Fast Charging",
      "display": "6.71 inches, 1440 x 3120 px, 120 Hz Display with Punch Hole",
      "camera": "50 MP + 48 MP + 12 MP Triple Rear & 11.1 MP Front Camera",
      "os": "Android v12",
      "fm_radio": "No FM Radio",
      "spec_score": "86",
      "availability": "Available",
      "store": "amazon"
    },
    {
      "model": "Google Pixel 9A",
      "original_price": "₹42,837",
      "final_price": "₹41,552",
      "network": "Dual Sim, 3G, 4G, 5G, VoLTE, Wi-Fi, NFC",
      "processor": "Tensor G4, Octa Core, 3.1 GHz Processor",
      "memory": "8 GB RAM, 256 GB inbuilt",
      "battery": "5100 mAh Battery with 23W Fast Charging",
      "display": "6.3 inches, 1080 x 2424 px, 120 Hz Display with Punch Hole",
      "camera": "48 MP + 13 MP Dual Rear & 13 MP Front Camera",
      "os": "Android v15",
      "fm_radio": "Memory Card Not Supported",
      "spec_score": "84",
      "availability": "Available",
      "store": "amazon"
    },
    {
      "model": "Google Pixel 10 Pro",
      "original_price": "₹1,09,999",
      "final_price": "₹1,08,899",
      "network": "Dual Sim, 3G, 4G, 5G, VoLTE, Vo5G, Wi-Fi, NFC",
      "processor": "Tensor G5",
      "memory": "16 GB RAM, 256 GB inbuilt",
      "battery": "4870 mAh Battery with 30W Fast Charging",
      "display": "6.3 inches, 1280 x 2856 px, 120 Hz Display with Punch Hole",
      "camera": "50 MP + 48 MP + 48 MP Triple Rear & 42 MP Front Camera",
      "os": "Android v16",
      "fm_radio": "No FM Radio",
      "spec_score": "83",
      "availability": "Available",
      "store": "croma"
    },
    {
      "model": "Google Pixel 8A",
      "original_price": "₹34,999",
      "final_price": "₹32,549",
      "network": "Dual Sim, 3G, 4G, 5G, VoLTE, Wi-Fi, NFC",
      "processor": "Tensor G3, Nine-Cores, 3 GHz Processor",
      "memory": "8 GB RAM, 128 GB inbuilt",
      "battery": "4492 mAh Battery with Fast Charging",
      "display": "6.1 inches, 1080 x 2400 px, 120 Hz Display with Punch Hole",
      "camera": "64 MP + 13 MP Dual Rear & 13 MP Front Camera",
      "os": "Android v14",
      "fm_radio": "Memory Card Not Supported",
      "spec_score": "76",
      "availability": "Available",
      "store": "croma"
    },
    {
      "model": "Google Pixel 7 Pro 5G",
      "original_price": "₹35,980",
      "final_price": "₹35,260",
      "network": "Dual Sim, 3G, 4G, 5G, VoLTE, Wi-Fi, NFC",
      "processor": "Google Tensor G2, Octa Core, 2.85 GHz Processor",
      "memory": "12 GB RAM, 128 GB inbuilt",
      "battery": "5000 mAh Battery with 30W Fast Charging",
      "display": "6.7 inches, 1440 x 3120 px, 120 Hz Display with Punch Hole",
      "camera": "50 MP + 48 MP + 12 MP Triple Rear & 10.8 MP Front Camera",
      "os": "Android v13",
      "fm_radio": "No FM Radio",
      "spec_score": "87",
      "availability": "Available",
      "store": "amazon"
    },
    {
      "model": "Google Pixel 10 Pro XL",
      "original_price": "₹1,24,999",
      "final_price": "₹1,24,999",
      "network": "Dual Sim, 3G, 4G, 5G, VoLTE, Vo5G, Wi-Fi, NFC",
      "processor": "Tensor G5",
      "memory": "16 GB RAM, 256 GB inbuilt",
      "battery": "5200 mAh Battery with 45W Fast Charging",
      "display": "6.8 inches, 1344 x 2992 px, 120 Hz Display with Punch Hole",
      "camera": "50 MP + 48 MP + 48 MP Triple Rear & 42 MP Front Camera",
      "os": "Android v16",
      "fm_radio": "No FM Radio",
      "spec_score": "84",
      "availability": "Available",
      "store": "croma"
    },
    {
      "model": "Google Pixel 9 Pro XL",
      "original_price": "₹89,999",
      "final_price": "₹79,199",
      "network": "Dual Sim, 3G, 4G, 5G, VoLTE, Vo5G, Wi-Fi, NFC",
      "processor": "Tensor G4, Octa Core, 3.1 GHz Processor",
      "memory": "16 GB RAM, 256 GB inbuilt",
      "battery": "5060 mAh Battery with 37W Fast Charging",
      "display": "6.8 inches, 1344 x 2992 px, 120 Hz Display with Punch Hole",
      "camera": "50 MP + 48 MP + 48 MP Triple Rear & 42 MP Front Camera",
      "os": "Android v14",
      "fm_radio": "No FM Radio",
      "spec_score": "91",
      "availability": "Available",
      "store": "flipkart"
    },
    {
      "model": "Google Pixel 7A",
      "original_price": "₹26,930",
      "final_price": "₹26,930",
      "network": "Dual Sim, 3G, 4G, 5G, VoLTE, Wi-Fi, NFC",
      "processor": "Tensor G2, Octa Core, 2.85 GHz Processor",
      "memory": "8 GB RAM, 128 GB inbuilt",
      "battery": "4385 mAh Battery with 18W Fast Charging",
      "display": "6.1 inches, 1080 x 2400 px, 90 Hz Display with Punch Hole",
      "camera": "64 MP + 13 MP Dual Rear & 13 MP Front Camera",
      "os": "Android v13",
      "fm_radio": "Memory Card Not Supported",
      "spec_score": "84",
      "availability": "Available",
      "store": "amazon"
    },
    {
      "model": "Google Pixel 10A",
      "original_price": "₹49,990",
      "final_price": "₹49,990",
      "network": "Dual Sim, 3G, 4G, 5G, VoLTE, Wi-Fi, NFC",
      "processor": "Tensor G4, Octa Core, 3.1 GHz Processor",
      "memory": "8 GB RAM, 128 GB inbuilt",
      "battery": "5200 mAh Battery with 20W Fast Charging",
      "display": "6.36 inches, 1080 x 2424 px, 120 Hz Display with Punch Hole",
      "camera": "50 MP + 13 MP Dual Rear & 12 MP Front Camera",
      "os": "Android v16",
      "fm_radio": "Memory Card Not Supported",
      "spec_score": "83",
      "availability": "Available",
      "store": "amazon"
    },
    {
      "model": "Google Pixel 8 5G",
      "original_price": "₹38,499",
      "final_price": "₹38,499",
      "network": "Dual Sim, 3G, 4G, 5G, VoLTE, Wi-Fi, NFC",
      "processor": "Tensor G3, Nine Core, 3 GHz Processor",
      "memory": "8 GB RAM, 128 GB inbuilt",
      "battery": "4575 mAh Battery with 30W Fast Charging",
      "display": "6.2 inches, 1080 x 2400 px, 120 Hz Display with Punch Hole",
      "camera": "50 MP + 12 MP Dual Rear & 10.5 MP Front Camera",
      "os": "Android v14",
      "fm_radio": "No FM Radio",
      "spec_score": "75",
      "availability": "UPCOMING",
      "store": "amazon"
    },
    {
      "model": "Google Pixel 6A",
      "original_price": "₹23,999",
      "final_price": "₹23,519",
      "network": "Dual Sim, 3G, 4G, 5G, VoLTE, Wi-Fi, NFC",
      "processor": "Google Tensor, Octa Core Processor",
      "memory": "6 GB RAM, 128 GB inbuilt",
      "battery": "4410 mAh Battery with Fast Charging",
      "display": "6.14 inches, 1080 x 2400 px Display with Punch Hole",
      "camera": "12.2 MP + 12 MP Dual Rear & 8 MP Front Camera",
      "os": "Android v12",
      "fm_radio": "Memory Card Not Supported",
      "spec_score": "70",
      "availability": "Available",
      "store": "amazon"
    },
    {
      "model": "Google Pixel 6 Pro (12GB RAM + 256GB)",
      "original_price": "₹32,999",
      "final_price": "₹32,009",
      "network": "Dual Sim, 3G, 4G, 5G, VoLTE, Wi-Fi, NFC",
      "processor": "Tensor, Octa Core, 2.8 GHz Processor",
      "memory": "12 GB RAM, 256 GB inbuilt",
      "battery": "5003 mAh Battery with 30W Fast Charging",
      "display": "6.71 inches, 1440 x 3120 px, 120 Hz Display with Punch Hole",
      "camera": "50 MP + 48 MP + 12 MP Triple Rear & 11.1 MP Front Camera",
      "os": "Android v12",
      "fm_radio": "No FM Radio",
      "spec_score": "87",
      "availability": "Available",
      "store": "amazon"
    },
    {
      "model": "Google Pixel 8 Pro",
      "original_price": "₹52,999",
      "final_price": "₹49,289",
      "network": "Dual Sim, 3G, 4G, 5G, VoLTE, Wi-Fi, NFC",
      "processor": "Tensor G3, Nine Cores, 3 GHz Processor",
      "memory": "12 GB RAM, 128 GB inbuilt",
      "battery": "5050 mAh Battery with 30W Fast Charging",
      "display": "6.7 inches, 1344 x 2992 px, 120 Hz Display with Punch Hole",
      "camera": "50 MP + 48 MP + 48 MP Triple Rear & 10.5 MP Front Camera",
      "os": "Android v14",
      "fm_radio": "No FM Radio",
      "spec_score": "79",
      "availability": "Available",
      "store": "amazon"
    },
    {
      "model": "Google Pixel 9 Pro",
      "original_price": "₹88,450",
      "final_price": "₹85,797",
      "network": "Dual Sim, 3G, 4G, 5G, VoLTE, Vo5G, Wi-Fi, NFC",
      "processor": "Tensor G4, Octa Core, 3.1 GHz Processor",
      "memory": "16 GB RAM, 256 GB inbuilt",
      "battery": "4700 mAh Battery with 27W Fast Charging",
      "display": "6.3 inches, 1280 x 2856 px, 120 Hz Display with Punch Hole",
      "camera": "50 MP + 48 MP + 48 MP Triple Rear & 42 MP Front Camera",
      "os": "Android v14",
      "fm_radio": "No FM Radio",
      "spec_score": "90",
      "availability": "Available",
      "store": "amazon"
    },
    {
      "model": "Google Pixel 6",
      "original_price": "₹23,490",
      "final_price": "₹23,490",
      "network": "Dual Sim, 3G, 4G, 5G, VoLTE, Wi-Fi, NFC",
      "processor": "Google Tensor, Octa Core, 2.8 GHz Processor",
      "memory": "8 GB RAM, 128 GB inbuilt",
      "battery": "4614 mAh Battery with 30W Fast Charging",
      "display": "6.4 inches, 1080 x 2400 px, 90 Hz Display with Punch Hole",
      "camera": "50 MP + 12 MP Dual Rear & 8 MP Front Camera",
      "os": "Android v12",
      "fm_radio": "No FM Radio",
      "spec_score": "82",
      "availability": "Available",
      "store": "amazon"
    },
    {
      "model": "Google Pixel 10 Pro Fold",
      "original_price": "₹1,72,999",
      "final_price": "₹1,72,999",
      "network": "Dual Sim, 3G, 4G, 5G, VoLTE, Wi-Fi, NFC",
      "processor": "Tensor G5",
      "memory": "16 GB RAM, 256 GB inbuilt",
      "battery": "5015 mAh Battery with 30W Fast Charging",
      "display": "8 inches, 2076 x 2152 px, 120 Hz Display with Punch Hole, Foldable Display, Dual Display",
      "camera": "48 MP + 10.8 MP + 10.5 MP Triple Rear & 10 MP + 10 MP Dual Front Camera",
      "os": "Android v16",
      "fm_radio": null,
      "spec_score": "83",
      "availability": "Available",
      "store": "croma"
    },
    {
      "model": "Google Pixel 9 Pro Fold",
      "original_price": "₹1,19,999",
      "final_price": "₹1,16,399",
      "network": "Dual Sim, 3G, 4G, 5G, VoLTE, Wi-Fi, NFC",
      "processor": "Tensor G4, Octa Core, 3.1 GHz Processor",
      "memory": "16 GB RAM, 256 GB inbuilt",
      "battery": "4650 mAh Battery with Fast Charging",
      "display": "8.03 inches, 2152 x 2076 px, 120 Hz Display with Punch Hole, Foldable Display, Dual Display",
      "camera": "48 MP + 10.8 MP + 10.5 MP Triple Rear & 10 MP + 10 MP Dual Front Camera",
      "os": "Android v14",
      "fm_radio": null,
      "spec_score": "91",
      "availability": "Available",
      "store": "flipkart"
    },
    {
      "model": "Google Pixel 7 5G",
      "original_price": "₹27,999",
      "final_price": "₹27,439",
      "network": "Dual Sim, 3G, 4G, 5G, VoLTE, Wi-Fi, NFC",
      "processor": "Google Tensor G2, Octa Core, 2.85 GHz Processor",
      "memory": "8 GB RAM, 128 GB inbuilt",
      "battery": "4355 mAh Battery with 30W Fast Charging",
      "display": "6.3 inches, 1080 x 2400 px, 90 Hz Display with Punch Hole",
      "camera": "50 MP + 12 MP Dual Rear & 10.8 MP Front Camera",
      "os": "Android v13",
      "fm_radio": "No FM Radio",
      "spec_score": "83",
      "availability": "Available",
      "store": "amazon"
    },
    {
      "model": "Google Pixel 8A (8GB RAM + 256GB)",
      "original_price": "₹41,999",
      "final_price": "₹40,319",
      "network": "Dual Sim, 3G, 4G, 5G, VoLTE, Wi-Fi, NFC",
      "processor": "Tensor G3, Nine-Cores, 3 GHz Processor",
      "memory": "8 GB RAM, 256 GB inbuilt",
      "battery": "4492 mAh Battery with Fast Charging",
      "display": "6.1 inches, 1080 x 2400 px, 120 Hz Display with Punch Hole",
      "camera": "64 MP + 13 MP Dual Rear & 13 MP Front Camera",
      "os": "Android v14",
      "fm_radio": "Memory Card Not Supported",
      "spec_score": "77",
      "availability": "Available",
      "store": "flipkart"
    },
    {
      "model": "Google Pixel 11 Pro",
      "original_price": "₹1,11,999",
      "final_price": "₹1,11,999",
      "network": "Dual Sim, 3G, 4G, 5G, VoLTE, Vo5G, Wi-Fi, NFC",
      "processor": "Tensor G6",
      "memory": "16 GB RAM, 256 GB inbuilt",
      "battery": "5000 mAh Battery with 35W Fast Charging",
      "display": "6.31 inches, 1280 x 2856 px, 144 Hz Display with Punch Hole",
      "camera": "50 MP + 50 MP + 50 MP Triple Rear & 48 MP Front Camera",
      "os": "Android v17",
      "fm_radio": "No FM Radio",
      "spec_score": "83",
      "availability": "RUMORED",
      "store": "amazon"
    },
    {
      "model": "Google Pixel 11",
      "original_price": "₹79,990",
      "final_price": "₹79,990",
      "network": "Dual Sim, 3G, 4G, 5G, VoLTE, Vo5G, Wi-Fi, NFC",
      "processor": "Google Tensor 6",
      "memory": "8 GB RAM, 256 GB inbuilt",
      "battery": "5500 mAh Battery with 65W Fast Charging",
      "display": "6.6 inches, 1080 x 2400 px, 120 Hz Display with Punch Hole",
      "camera": "50 MP + 50 MP Dual Rear & 50 MP Front Camera",
      "os": "Android v15",
      "fm_radio": "No FM Radio",
      "spec_score": "79",
      "availability": "RUMORED",
      "store": "amazon"
    },
    {
      "model": "Google Pixel 9 Pro XL (16GB RAM + 512GB)",
      "original_price": "₹1,39,999",
      "final_price": "₹1,18,999",
      "network": "Dual Sim, 3G, 4G, 5G, VoLTE, Vo5G, Wi-Fi, NFC",
      "processor": "Tensor G4, Octa Core, 3.1 GHz Processor",
      "memory": "16 GB RAM, 512 GB inbuilt",
      "battery": "5060 mAh Battery with 37W Fast Charging",
      "display": "6.8 inches, 1344 x 2992 px, 120 Hz Display with Punch Hole",
      "camera": "50 MP + 48 MP + 48 MP Triple Rear & 42 MP Front Camera",
      "os": "Android v14",
      "fm_radio": "No FM Radio",
      "spec_score": "91",
      "availability": "Available",
      "store": "croma"
    },
    {
      "model": "Google Pixel 9A (8GB RAM + 128GB)",
      "original_price": "₹46,999",
      "final_price": "₹46,999",
      "network": "Dual Sim, 3G, 4G, 5G, VoLTE, Wi-Fi, NFC",
      "processor": "Tensor G4, Octa Core, 3.1 GHz Processor",
      "memory": "8 GB RAM, 128 GB inbuilt",
      "battery": "5100 mAh Battery with 23W Fast Charging",
      "display": "6.3 inches, 1080 x 2424 px, 120 Hz Display with Punch Hole",
      "camera": "48 MP + 13 MP Dual Rear & 13 MP Front Camera",
      "os": "Android v15",
      "fm_radio": "Memory Card Not Supported",
      "spec_score": "84",
      "availability": "UPCOMING",
      "store": "amazon"
    },
    {
      "model": "Google Pixel 9 Pro XL (16GB RAM + 128GB)",
      "original_price": "₹99,999",
      "final_price": "₹99,999",
      "network": "Dual Sim, 3G, 4G, 5G, VoLTE, Vo5G, Wi-Fi, NFC",
      "processor": "Tensor G4, Octa Core, 3.1 GHz Processor",
      "memory": "16 GB RAM, 128 GB inbuilt",
      "battery": "5060 mAh Battery with 37W Fast Charging",
      "display": "6.8 inches, 1344 x 2992 px, 120 Hz Display with Punch Hole",
      "camera": "50 MP + 48 MP + 48 MP Triple Rear & 42 MP Front Camera",
      "os": "Android v14",
      "fm_radio": "No FM Radio",
      "spec_score": "90",
      "availability": "UPCOMING",
      "store": "amazon"
    },
    {
      "model": "Google Pixel 8 Pro (12GB RAM + 256 GB)",
      "original_price": "₹79,999",
      "final_price": "₹75,999",
      "network": "Dual Sim, 3G, 4G, 5G, VoLTE, Wi-Fi, NFC",
      "processor": "Tensor G3, Nine Cores, 3 GHz Processor",
      "memory": "12 GB RAM, 256 GB inbuilt",
      "battery": "5050 mAh Battery with 30W Fast Charging",
      "display": "6.7 inches, 1344 x 2992 px, 120 Hz Display with Punch Hole",
      "camera": "50 MP + 48 MP + 48 MP Triple Rear & 10.5 MP Front Camera",
      "os": "Android v14",
      "fm_radio": "No FM Radio",
      "spec_score": "79",
      "availability": "Available",
      "store": "flipkart"
    },
    {
      "model": "Google Pixel Fold",
      "original_price": "₹1,46,990",
      "final_price": "₹1,46,990",
      "network": "Dual Sim, 3G, 4G, 5G, VoLTE, Wi-Fi, NFC",
      "processor": "Google Tensor G2, Octa Core, 2.85 GHz Processor",
      "memory": "12 GB RAM, 256 GB inbuilt",
      "battery": "4821 mAh Battery with 30W Fast Charging",
      "display": "7.6 inches, 1840 x 2208 px, 120 Hz Display with Punch Hole, Foldable Display, Dual Display",
      "camera": "48 MP + 10.8 MP + 10.8 MP Triple Rear & 9.5 MP + 8 MP Dual Front Camera",
      "os": "Android v13",
      "fm_radio": null,
      "spec_score": "88",
      "availability": "UPCOMING",
      "store": "amazon"
    },
    {
      "model": "Google Pixel 7 Ultra",
      "original_price": "₹89,999",
      "final_price": "₹89,999",
      "network": "Dual Sim, 3G, 4G, 5G, VoLTE, Wi-Fi, NFC",
      "processor": "Google Tensor G2, Octa Core, 2.85 GHz Processor",
      "memory": "12 GB RAM, 128 GB inbuilt",
      "battery": "5000 mAh Battery with 30W Fast Charging",
      "display": "6.7 inches, 1440 x 3120 px, 120 Hz Display with Punch Hole",
      "camera": "64 MP + 48 MP + 12 MP Triple Rear & 10.8 MP Front Camera",
      "os": "Android v13",
      "fm_radio": "No FM Radio",
      "spec_score": "88",
      "availability": "RUMORED",
      "store": "amazon"
    },
    {
      "model": "Google Pixel Fold 2",
      "original_price": "₹1,59,990",
      "final_price": "₹1,59,990",
      "network": "Dual Sim, 3G, 4G, 5G, VoLTE, Wi-Fi, NFC",
      "processor": "Tensor G4",
      "memory": "12 GB RAM, 256 GB inbuilt",
      "battery": "5000 mAh Battery with 45W Fast Charging",
      "display": "8.02 inches, 1840 x 2208 px, 120 Hz Display with Punch Hole, Foldable Display, Dual Display",
      "camera": "50 MP + 10.8 MP + 10.8 MP Triple Rear & 12 MP + 12 MP Dual Front Camera",
      "os": "Android v14",
      "fm_radio": null,
      "spec_score": "82",
      "availability": "RUMORED",
      "store": "amazon"
    },
    {
      "model": "Google Pixel Flip",
      "original_price": "₹99,990",
      "final_price": "₹99,990",
      "network": "Single Sim, 3G, 4G, 5G, VoLTE, Vo5G, Wi-Fi, NFC",
      "processor": "Tensor G2, Octa Core, 2.85 GHz Processor",
      "memory": "8 GB RAM, 128 GB inbuilt",
      "battery": "4000 mAh Battery with 45W Fast Charging",
      "display": "6.7 inches, 1080 x 2640 px, 120 Hz Display with Punch Hole, Foldable Display, Dual Display",
      "camera": "48 MP + 12 MP Dual Rear & 10 MP Front Camera",
      "os": "Memory Card Not Supported",
      "fm_radio": null,
      "spec_score": "88",
      "availability": "UPCOMING",
      "store": "amazon"
    },
    {
      "model": "Google Pixel Notepad",
      "original_price": "₹1,25,990",
      "final_price": "₹1,25,990",
      "network": "Dual Sim, 3G, 4G, 5G, VoLTE, Wi-Fi, NFC",
      "processor": "Google Tensor 2, Octa Core Processor",
      "memory": "12 GB RAM, 128 GB inbuilt",
      "battery": "5003 mAh Battery with 30W Fast Charging",
      "display": "8.3 inches, 1940 x 3120 px, 120 Hz Display with Punch Hole",
      "camera": "50 MP + 48 MP + 12 MP Triple Rear & 12 MP Front Camera",
      "os": "Android v12",
      "fm_radio": "No FM Radio",
      "spec_score": "81",
      "availability": "RUMORED",
      "store": "amazon"
    },
    {
      "model": "Google Pixel 5A",
      "original_price": "₹32,999",
      "final_price": "₹32,999",
      "network": "Single Sim, 3G, 4G, 5G, VoLTE, Wi-Fi, NFC",
      "processor": "Snapdragon 765G, Octa Core, 2.4 GHz Processor",
      "memory": "6 GB RAM, 128 GB inbuilt",
      "battery": "4620 mAh Battery with 18W Fast Charging",
      "display": "6.34 inches, 1080 x 2400 px Display with Punch Hole",
      "camera": "16 MP + 12.2 MP Dual Rear & 8 MP Front Camera",
      "os": "Android v11",
      "fm_radio": "No FM Radio",
      "spec_score": "76",
      "availability": "UPCOMING",
      "store": "amazon"
    },
    {
      "model": "Google Pixel 8 (8GB RAM + 256 GB)",
      "original_price": "₹50,999",
      "final_price": "₹50,999",
      "network": "Dual Sim, 3G, 4G, 5G, VoLTE, Wi-Fi, NFC",
      "processor": "Tensor G3, Nine Core, 3 GHz Processor",
      "memory": "8 GB RAM, 256 GB inbuilt",
      "battery": "4575 mAh Battery with 30W Fast Charging",
      "display": "6.2 inches, 1080 x 2400 px, 120 Hz Display with Punch Hole",
      "camera": "50 MP + 12 MP Dual Rear & 10.5 MP Front Camera",
      "os": "Android v14",
      "fm_radio": "No FM Radio",
      "spec_score": "76",
      "availability": "OUT OF STOCK",
      "store": "flipkart"
    },
    {
      "model": "Google Pixel 7 Pro 5G (12GB RAM + 512GB)",
      "original_price": "₹93,990",
      "final_price": "₹93,990",
      "network": "Dual Sim, 3G, 4G, 5G, VoLTE, Wi-Fi, NFC",
      "processor": "Google Tensor G2, Octa Core, 2.85 GHz Processor",
      "memory": "12 GB RAM, 512 GB inbuilt",
      "battery": "5000 mAh Battery with 30W Fast Charging",
      "display": "6.7 inches, 1440 x 3120 px, 120 Hz Display with Punch Hole",
      "camera": "50 MP + 48 MP + 12 MP Triple Rear & 10.8 MP Front Camera",
      "os": "Android v13",
      "fm_radio": "No FM Radio",
      "spec_score": "89",
      "availability": "OUT OF STOCK",
      "store": "amazon"
    },
    {
      "model": "Google Pixel 6 Pro (12GB RAM + 512GB)",
      "original_price": "₹65,000",
      "final_price": "₹65,000",
      "network": "Dual Sim, 3G, 4G, 5G, VoLTE, Wi-Fi, NFC",
      "processor": "Tensor, Octa Core, 2.8 GHz Processor",
      "memory": "12 GB RAM, 512 GB inbuilt",
      "battery": "5003 mAh Battery with 30W Fast Charging",
      "display": "6.71 inches, 1440 x 3120 px, 120 Hz Display with Punch Hole",
      "camera": "50 MP + 48 MP + 12 MP Triple Rear & 11.1 MP Front Camera",
      "os": "Android v12",
      "fm_radio": "No FM Radio",
      "spec_score": "88",
      "availability": "OUT OF STOCK",
      "store": "amazon"
    },
    {
      "model": "Google Pixel 6 5G (8GB RAM + 256GB)",
      "original_price": "₹24,999",
      "final_price": "₹24,999",
      "network": "Dual Sim, 3G, 4G, 5G, VoLTE, Wi-Fi, NFC",
      "processor": "Google Tensor, Octa Core, 2.8 GHz Processor",
      "memory": "8 GB RAM, 256 GB inbuilt",
      "battery": "4614 mAh Battery with 30W Fast Charging",
      "display": "6.4 inches, 1080 x 2400 px, 90 Hz Display with Punch Hole",
      "camera": "50 MP + 12 MP Dual Rear & 8 MP Front Camera",
      "os": "Android v12",
      "fm_radio": "No FM Radio",
      "spec_score": "82",
      "availability": "OUT OF STOCK",
      "store": "amazon"
    },
    {
      "model": "Google Pixel 7 5G (8GB RAM + 256GB)",
      "original_price": "₹59,990",
      "final_price": "₹59,990",
      "network": "Dual Sim, 3G, 4G, 5G, VoLTE, Wi-Fi, NFC",
      "processor": "Google Tensor G2, Octa Core, 2.85 GHz Processor",
      "memory": "8 GB RAM, 256 GB inbuilt",
      "battery": "4355 mAh Battery with 30W Fast Charging",
      "display": "6.3 inches, 1080 x 2400 px, 90 Hz Display with Punch Hole",
      "camera": "50 MP + 12 MP Dual Rear & 10.8 MP Front Camera",
      "os": "Android v13",
      "fm_radio": "No FM Radio",
      "spec_score": "85",
      "availability": "OUT OF STOCK",
      "store": "amazon"
    },
    {
      "model": "Google Pixel 4a 5G",
      "original_price": "₹18,999",
      "final_price": "₹18,999",
      "network": "Dual Sim, 3G, 4G, 5G, VoLTE, Wi-Fi, NFC",
      "processor": "Snapdragon 765G, Octa Core, 2.4 GHz Processor",
      "memory": "6 GB RAM, 128 GB inbuilt",
      "battery": "3885 mAh Battery with 18W Fast Charging",
      "display": "6.2 inches, 1080 x 2340 px Display with Punch Hole",
      "camera": "16 MP + 12.2 MP Dual Rear & 8 MP Front Camera",
      "os": "Android v11",
      "fm_radio": "Bluetooth",
      "spec_score": "75",
      "availability": "OUT OF STOCK",
      "store": "amazon"
    },
    {
      "model": "Google Pixel 5 XL",
      "original_price": "₹92,990",
      "final_price": "₹92,990",
      "network": "Dual Sim, 3G, 4G, VoLTE, Wi-Fi, NFC",
      "processor": "Snapdragon 865, Octa Core, 2.84 GHz Processor",
      "memory": "6 GB RAM, 64 GB inbuilt",
      "battery": "4000 mAh Battery with Fast Charging",
      "display": "6.3 inches, 1440 x 2960 px Display",
      "camera": "16 MP Rear & 13 MP Front Camera",
      "os": "Android v10",
      "fm_radio": "Memory Card Not Supported",
      "spec_score": "74",
      "availability": "OUT OF STOCK",
      "store": "amazon"
    },
    {
      "model": "Google Pixel 5",
      "original_price": "₹28,980",
      "final_price": "₹28,980",
      "network": "Dual Sim, 3G, 4G, 5G, VoLTE, Wi-Fi, NFC",
      "processor": "Snapdragon 765G, Octa Core, 2.4 GHz Processor",
      "memory": "8 GB RAM, 128 GB inbuilt",
      "battery": "4080 mAh Battery with 18W Fast Charging",
      "display": "6 inches, 1080 x 2340 px, 90 Hz Display with Punch Hole",
      "camera": "16 MP + 12.2 MP Dual Rear & 8 MP Front Camera",
      "os": "Android v11",
      "fm_radio": "Bluetooth",
      "spec_score": "80",
      "availability": "OUT OF STOCK",
      "store": "amazon"
    },
    {
      "model": "Google Pixel 4A",
      "original_price": "₹19,990",
      "final_price": "₹19,990",
      "network": "Dual Sim, 3G, 4G, VoLTE, Wi-Fi, NFC",
      "processor": "Snapdragon 730G, Octa Core, 2.2 GHz Processor",
      "memory": "6 GB RAM, 128 GB inbuilt",
      "battery": "3140 mAh Battery with 18W Fast Charging",
      "display": "5.81 inches, 1080 x 2340 px Display with Punch Hole",
      "camera": "12.2 MP Rear & 8 MP Front Camera",
      "os": "Android v10",
      "fm_radio": "No FM Radio",
      "spec_score": "70",
      "availability": "OUT OF STOCK",
      "store": "amazon"
    },
    {
      "model": "Google Pixel 4 XL",
      "original_price": "₹32,990",
      "final_price": "₹32,990",
      "network": "Dual Sim, 3G, 4G, VoLTE, Wi-Fi, NFC",
      "processor": "Snapdragon 855, Octa Core, 2.8 GHz Processor",
      "memory": "6 GB RAM, 64 GB inbuilt",
      "battery": "3700 mAh Battery with Fast Charging",
      "display": "6.3 inches, 1440 x 3040 px Display",
      "camera": "16 MP + 12.2 MP Dual Rear & 8 MP + TOF 3D Dual Front Camera",
      "os": "Android v10",
      "fm_radio": "Memory Card Not Supported",
      "spec_score": "78",
      "availability": "OUT OF STOCK",
      "store": "amazon"
    },
    {
      "model": "Google Pixel 4",
      "original_price": "₹16,999",
      "final_price": "₹16,999",
      "network": "Dual Sim, 3G, 4G, VoLTE, Wi-Fi, NFC",
      "processor": "Snapdragon 855, Octa Core, 2.8 GHz Processor",
      "memory": "6 GB RAM, 64 GB inbuilt",
      "battery": "2800 mAh Battery with Fast Charging",
      "display": "5.7 inches, 1080 x 2280 px Display",
      "camera": "16 MP + 12.2 MP Dual Rear & 8 MP + TOF 3D Dual Front Camera",
      "os": "Android v10",
      "fm_radio": "Memory Card Not Supported",
      "spec_score": "76",
      "availability": "OUT OF STOCK",
      "store": "amazon"
    },
    {
      "model": "Google Pixel 3 XL",
      "original_price": "₹19,499",
      "final_price": "₹19,499",
      "network": "Single Sim, 3G, 4G, VoLTE, Wi-Fi, NFC",
      "processor": "Snapdragon 845, Octa Core, 2.8 GHz Processor",
      "memory": "4 GB RAM, 64 GB inbuilt",
      "battery": "3430 mAh Battery with Fast Charging",
      "display": "6.3 inches, 1440 x 2960 px Display with Small Notch",
      "camera": "12.2 MP Rear & 8 MP + 8 MP Dual Front Camera",
      "os": "Android v9.0 (Pie)",
      "fm_radio": "No FM Radio",
      "spec_score": "69",
      "availability": "OUT OF STOCK",
      "store": "amazon"
    },
    {
      "model": "Google Pixel 2 XL",
      "original_price": "₹15,490",
      "final_price": "₹15,490",
      "network": "Single Sim, 3G, 4G, VoLTE, Wi-Fi, NFC",
      "processor": "Snapdragon 835, Octa Core, 2.35 GHz Processor",
      "memory": "4 GB RAM, 128 GB inbuilt",
      "battery": "3520 mAh Battery with Fast Charging",
      "display": "6 inches, 1440 x 2880 px Display",
      "camera": "12.2 MP Rear & 8 MP Front Camera",
      "os": "Android v8.0 (Oreo)",
      "fm_radio": "Memory Card Not Supported",
      "spec_score": "68",
      "availability": "OUT OF STOCK",
      "store": "amazon"
    },
    {
      "model": "Google Pixel 2",
      "original_price": "₹19,490",
      "final_price": "₹19,490",
      "network": "Single Sim, 3G, 4G, VoLTE, Wi-Fi, NFC",
      "processor": "Snapdragon 835, Octa Core, 2.45 GHz Processor",
      "memory": "4 GB RAM, 128 GB inbuilt",
      "battery": "2700 mAh Battery with Fast Charging",
      "display": "5 inches, 1080 x 1920 px Display",
      "camera": "12.2 MP Rear & 8 MP Front Camera",
      "os": "Android v8.0 (Oreo)",
      "fm_radio": "Memory Card Not Supported",
      "spec_score": "67",
      "availability": "OUT OF STOCK",
      "store": "amazon"
    },
    {
      "model": "Google Pixel (128GB)",
      "original_price": "₹22,299",
      "final_price": "₹22,299",
      "network": "Single Sim, 3G, 4G, VoLTE, Wi-Fi, NFC",
      "processor": "Snapdragon 821, Quad Core, 2.15 GHz Processor",
      "memory": "4 GB RAM, 128 GB inbuilt",
      "battery": "2770 mAh Battery with Fast Charging",
      "display": "5 inches, 1080 x 1920 px Display",
      "camera": "12.3 MP Rear & 8 MP Front Camera",
      "os": "Android v7.1 (Nougat)",
      "fm_radio": "Memory Card Not Supported",
      "spec_score": "63",
      "availability": "OUT OF STOCK",
      "store": "amazon"
    },
    {
      "model": "Google Nexus 6 (64GB)",
      "original_price": "₹21,999",
      "final_price": "₹21,999",
      "network": "Single Sim, 3G, 4G, Wi-Fi, NFC",
      "processor": "Quad Core, 2.7 GHz Processor",
      "memory": "3 GB RAM, 64 GB inbuilt",
      "battery": "3220 mAh Battery",
      "display": "6 inches, 2560 x 1440 px Display",
      "camera": "13 MP Rear & 2 MP Front Camera",
      "os": "Android v5 (Lollipop)",
      "fm_radio": "No FM Radio",
      "spec_score": "59",
      "availability": "OUT OF STOCK",
      "store": "flipkart"
    },
    {
      "model": "Google Pixel 8 Pro (12GB RAM + 512GB)",
      "original_price": "₹94,990",
      "final_price": "₹94,990",
      "network": "Dual Sim, 3G, 4G, 5G, VoLTE, Wi-Fi, NFC",
      "processor": "Tensor G3, Nine Cores, 3 GHz Processor",
      "memory": "12 GB RAM, 512 GB inbuilt",
      "battery": "5050 mAh Battery with 30W Fast Charging",
      "display": "6.7 inches, 1344 x 2992 px, 120 Hz Display with Punch Hole",
      "camera": "50 MP + 48 MP + 48 MP Triple Rear & 10.5 MP Front Camera",
      "os": "Android v14",
      "fm_radio": "No FM Radio",
      "spec_score": "80",
      "availability": "OUT OF STOCK",
      "store": "amazon"
    },
    {
      "model": "Google Pixel 6 XL",
      "original_price": "₹74,990",
      "final_price": "₹74,990",
      "network": "Dual Sim, 3G, 4G, 5G, VoLTE, Wi-Fi, NFC",
      "processor": "Snapdragon 888, Octa Core, 2.84 GHz Processor",
      "memory": "8 GB RAM, 128 GB inbuilt",
      "battery": "4800 mAh Battery with Fast Charging",
      "display": "6.2 inches, 1080 x 2400 px Display with Punch Hole",
      "camera": "16 MP + 16 MP + 12 MP Triple Rear & 16 MP Front Camera",
      "os": "Android v11",
      "fm_radio": "Memory Card Not Supported",
      "spec_score": "83",
      "availability": "OUT OF STOCK",
      "store": "amazon"
    },
    {
      "model": "Google Pixel 5 Pro",
      "original_price": "₹74,990",
      "final_price": "₹74,990",
      "network": "Dual Sim, 3G, 4G, VoLTE, Wi-Fi, NFC",
      "processor": "Snapdragon 865, Octa Core, 2.84 GHz Processor",
      "memory": "6 GB RAM, 64 GB inbuilt",
      "battery": "4000 mAh Battery with Fast Charging",
      "display": "6.3 inches, 1440 x 2960 px Display with Punch Hole",
      "camera": "16 MP Rear & 13 MP Front Camera",
      "os": "Android v10",
      "fm_radio": "Memory Card Not Supported",
      "spec_score": "74",
      "availability": "OUT OF STOCK",
      "store": "amazon"
    },
    {
      "model": "Google Pixel 5S",
      "original_price": "₹49,990",
      "final_price": "₹49,990",
      "network": "Dual Sim, 3G, 4G, VoLTE, Wi-Fi, NFC",
      "processor": "Snapdragon 765G, Octa Core, 2.4 GHz Processor",
      "memory": "6 GB RAM, 128 GB inbuilt",
      "battery": "3700 mAh Battery with Fast Charging",
      "display": "5.8 inches, 1080 x 2280 px Display with Punch Hole",
      "camera": "12 MP + 12 MP + 12 MP Triple Rear & 8 MP Front Camera",
      "os": "Android v10",
      "fm_radio": "Memory Card Not Supported",
      "spec_score": "75",
      "availability": "OUT OF STOCK",
      "store": "amazon"
    },
    {
      "model": "Google Pixel 4A XL",
      "original_price": "₹44,990",
      "final_price": "₹44,990",
      "network": "Dual Sim, 3G, 4G, 5G, VoLTE, Wi-Fi",
      "processor": "Snapdragon 765G, Octa Core, 2.4 GHz Processor",
      "memory": "6 GB RAM, 64 GB inbuilt",
      "battery": "3900 mAh Battery with Fast Charging",
      "display": "6.1 inches, 1080 x 2160 px Display with Punch Hole",
      "camera": "12.2 MP + 8 MP Dual Rear & 8 MP Front Camera",
      "os": "Android v10",
      "fm_radio": "Memory Card Not Supported",
      "spec_score": "72",
      "availability": "OUT OF STOCK",
      "store": "amazon"
    },
    {
      "model": "Google Pixel 3a",
      "original_price": "₹10,999",
      "final_price": "₹10,999",
      "network": "Single Sim, 3G, 4G, VoLTE, Wi-Fi, NFC",
      "processor": "Qualcomm Snapdragon 670, Octa Core, 2 GHz Processor",
      "memory": "4 GB RAM, 64 GB inbuilt",
      "battery": "3000 mAh Battery with 18W Fast Charging",
      "display": "5.6 inches, 1080 x 2220 px Display",
      "camera": "12.2 MP Rear & 8 MP Front Camera",
      "os": "Android v9.0 (Pie)",
      "fm_radio": "No FM Radio",
      "spec_score": "65",
      "availability": "OUT OF STOCK",
      "store": "amazon"
    },
    {
      "model": "Google Pixel 3a XL",
      "original_price": "₹14,999",
      "final_price": "₹14,999",
      "network": "Single Sim, 3G, 4G, VoLTE, Wi-Fi, NFC",
      "processor": "Qualcomm Snapdragon 670, Octa Core, 2 GHz Processor",
      "memory": "4 GB RAM, 64 GB inbuilt",
      "battery": "3700 mAh Battery with 18W Fast Charging",
      "display": "6 inches, 1080 x 2160 px Display",
      "camera": "12.2 MP Rear & 8 MP Front Camera",
      "os": "Android v9.0 (Pie)",
      "fm_radio": "No FM Radio",
      "spec_score": "66",
      "availability": "OUT OF STOCK",
      "store": "amazon"
    },
    {
      "model": "Google Pixel 3 Lite",
      "original_price": "₹41,990",
      "final_price": "₹41,990",
      "network": "Single Sim, 3G, 4G, VoLTE, Wi-Fi, NFC",
      "processor": "Snapdragon 670, Octa Core, 2 GHz Processor",
      "memory": "4 GB RAM, 32 GB inbuilt",
      "battery": "2915 mAh Battery with Fast Charging",
      "display": "5.56 inches, 1080 x 2220 px Display",
      "camera": "12.2 MP Rear & 8 MP Front Camera",
      "os": "Android v9.0 (Pie)",
      "fm_radio": "Memory Card Not Supported",
      "spec_score": "62",
      "availability": "OUT OF STOCK",
      "store": "amazon"
    },
    {
      "model": "Google Pixel 3 (128GB)",
      "original_price": "₹80,000",
      "final_price": "₹80,000",
      "network": "Single Sim, 3G, 4G, VoLTE, Wi-Fi, NFC",
      "processor": "Snapdragon 845, Octa Core, 2.8 GHz Processor",
      "memory": "4 GB RAM, 128 GB inbuilt",
      "battery": "2915 mAh Battery with Fast Charging",
      "display": "5.5 inches, 1080 x 2160 px Display",
      "camera": "12.2 MP Rear & 8 MP + 8 MP Dual Front Camera",
      "os": "Android v9.0 (Pie)",
      "fm_radio": "No FM Radio",
      "spec_score": "69",
      "availability": "OUT OF STOCK",
      "store": "amazon"
    },
    {
      "model": "Google Pixel 3 XL (128GB)",
      "original_price": "₹18,999",
      "final_price": "₹18,999",
      "network": "Single Sim, 3G, 4G, VoLTE, Wi-Fi, NFC",
      "processor": "Snapdragon 845, Octa Core, 2.8 GHz Processor",
      "memory": "4 GB RAM, 128 GB inbuilt",
      "battery": "3430 mAh Battery with Fast Charging",
      "display": "6.3 inches, 1440 x 2960 px Display with Small Notch",
      "camera": "12.2 MP Rear & 8 MP + 8 MP Dual Front Camera",
      "os": "Android v9.0 (Pie)",
      "fm_radio": "No FM Radio",
      "spec_score": "71",
      "availability": "OUT OF STOCK",
      "store": "amazon"
    },
    {
      "model": "Google Pixel 3",
      "original_price": "₹21,500",
      "final_price": "₹21,500",
      "network": "Single Sim, 3G, 4G, VoLTE, Wi-Fi, NFC",
      "processor": "Snapdragon 845, Octa Core, 2.8 GHz Processor",
      "memory": "4 GB RAM, 64 GB inbuilt",
      "battery": "2915 mAh Battery with Fast Charging",
      "display": "5.5 inches, 1080 x 2160 px Display",
      "camera": "12.2 MP Rear & 8 MP + 8 MP Dual Front Camera",
      "os": "Android v9.0 (Pie)",
      "fm_radio": "No FM Radio",
      "spec_score": "69",
      "availability": "OUT OF STOCK",
      "store": "amazon"
    },
    {
      "model": "Google Pixel 2 (64GB)",
      "original_price": "₹14,990",
      "final_price": "₹14,990",
      "network": "Single Sim, 3G, 4G, VoLTE, Wi-Fi, NFC",
      "processor": "Snapdragon 835, Octa Core, 2.45 GHz Processor",
      "memory": "4 GB RAM, 64 GB inbuilt",
      "battery": "2700 mAh Battery with Fast Charging",
      "display": "5 inches, 1080 x 1920 px Display",
      "camera": "12.2 MP Rear & 8 MP Front Camera",
      "os": "Android v8.0 (Oreo)",
      "fm_radio": "Memory Card Not Supported",
      "spec_score": "66",
      "availability": "OUT OF STOCK",
      "store": "amazon"
    },
    {
      "model": "Google Pixel 2 XL (64GB)",
      "original_price": "₹19,990",
      "final_price": "₹19,990",
      "network": "Single Sim, 3G, 4G, VoLTE, Wi-Fi, NFC",
      "processor": "Snapdragon 835, Octa Core, 2.35 GHz Processor",
      "memory": "4 GB RAM, 64 GB inbuilt",
      "battery": "3520 mAh Battery with Fast Charging",
      "display": "6 inches, 1440 x 2880 px Display",
      "camera": "12.2 MP Rear & 8 MP Front Camera",
      "os": "Android v8.0 (Oreo)",
      "fm_radio": "Memory Card Not Supported",
      "spec_score": "67",
      "availability": "OUT OF STOCK",
      "store": "amazon"
    },
    {
      "model": "Google Pixel",
      "original_price": "₹24,995",
      "final_price": "₹24,995",
      "network": "Single Sim, 3G, 4G, VoLTE, Wi-Fi, NFC",
      "processor": "Snapdragon 821, Quad Core, 2.15 GHz Processor",
      "memory": "4 GB RAM, 32 GB inbuilt",
      "battery": "2770 mAh Battery with Fast Charging",
      "display": "5 inches, 1080 x 1920 px Display",
      "camera": "12.3 MP Rear & 8 MP Front Camera",
      "os": "Android v7.1 (Nougat)",
      "fm_radio": "Memory Card Not Supported",
      "spec_score": "61",
      "availability": "OUT OF STOCK",
      "store": "amazon"
    },
    {
      "model": "Google Pixel XL (128GB)",
      "original_price": "₹17,999",
      "final_price": "₹17,999",
      "network": "Single Sim, 3G, 4G, VoLTE, Wi-Fi, NFC",
      "processor": "Snapdragon 821, Quad Core, 2.15 GHz Processor",
      "memory": "4 GB RAM, 128 GB inbuilt",
      "battery": "3450 mAh Battery with Fast Charging",
      "display": "5.5 inches, 1440 x 2560 px Display",
      "camera": "12.3 MP Rear & 8 MP Front Camera",
      "os": "Android v7.1 (Nougat)",
      "fm_radio": "Memory Card Not Supported",
      "spec_score": "65",
      "availability": "OUT OF STOCK",
      "store": "amazon"
    },
    {
      "model": "Google Pixel XL",
      "original_price": "₹15,950",
      "final_price": "₹15,950",
      "network": "Single Sim, 3G, 4G, VoLTE, Wi-Fi, NFC",
      "processor": "Snapdragon 821, Quad Core, 2.15 GHz Processor",
      "memory": "4 GB RAM, 32 GB inbuilt",
      "battery": "3450 mAh Battery with Fast Charging",
      "display": "5.5 inches, 1440 x 2560 px Display",
      "camera": "12.3 MP Rear & 8 MP Front Camera",
      "os": "Android v7.1 (Nougat)",
      "fm_radio": "Memory Card Not Supported",
      "spec_score": "61",
      "availability": "OUT OF STOCK",
      "store": "amazon"
    }
  ]
}

